Workbook
Name CONCESSÃO: #REF!
Name emenda: #REF!
Name Estados: #REF!
Name Estados_UF: #REF!
Name FNDE: #REF!
Name jjhkjh: #REF!
Name Municipios: #REF!
Name Previsao_dos_Fundos_PREVISFUNDO_Listar: #REF!
Name saljdalçfakjsd: #REF!

Sheet COM CORREÇÃO
A1: UF | B1: Ente Federado | C1: Código IBGE | D1: FPM | E1: FPE | F1: IPI-Exp | G1: AFE EC 123 | H1: ITR | I1: ICMS | J1: IPVA | K1: ITCMD | L1: Fundeb (Contribuição e complementação VAAF) | M1: IPTU | N1: IRRF | O1: ITBI | P1: ISS | Q1: IOF-Ouro | R1: Petróleo e Gás | S1: PNAE | T1: PNATE | U1: PDDE | V1: Quotas Estaduais e Municipais do Salário-Educação | W1: PNLD | X1: Total
A2: RO | B2: Rondônia | C2: 11 | D2: 0 | E2: 2.7151321e+08 | F2: 1034935 | G2: 11591613 | H2: 0 | I2: 2.6024932e+08 | J2: 17826211 | K2: 1821593.2 | L2: 1.621574e+09 | M2: 0 | N2: 2.3014492e+08 | O2: 0 | P2: 0 | Q2: 208962.76 | R2: 0 | S2: 23294058 | T2: 4218070.1 | U2: 4756221.2 | V2: 32816161 | W2: 8255503.3 | X2: =SUM(D2:W2) -> 2.4893048e+09
A3: AC | B3: Acre | C3: 12 | D3: 0 | E3: 3.248333e+08 | F3: 38016.873 | G3: 2549476.3 | H3: 0 | I3: 81248903 | J3: 3725980.4 | K3: 889362.26 | L3: 1.2134496e+09 | M3: 0 | N3: 1.7790999e+08 | O3: 0 | P3: 0 | Q3: 0 | R3: 0 | S3: 14348722 | T3: 4447634.6 | U3: 4819357.6 | V3: 11759447 | W3: 6732759.1 | X3: =SUM(D3:W3) -> 1.8467525e+09
A4: AM | B4: Amazonas | C4: 13 | D4: 0 | E4: 3.0794035e+08 | F4: 1131161.2 | G4: 5846796 | H4: 0 | I4: 6.0591792e+08 | J4: 22112264 | K4: 2617738.4 | L4: 2.8797992e+09 | M4: 0 | N4: 3.69603e+08 | O4: 0 | P4: 0 | Q4: 22305.889 | R4: 0 | S4: 60634993 | T4: 0 | U4: 5840286.3 | V4: 83426887 | W4: 22130762 | X4: =SUM(D4:W4) -> 4.3670237e+09
A5: RR | B5: Roraima | C5: 14 | D5: 0 | E5: 2.5570747e+08 | F5: 334764.38 | G5: 0 | H5: 0 | I5: 65202550 | J5: 3256109.1 | K5: 454821.18 | L5: 8.4820765e+08 | M5: 0 | N5: 1.1534782e+08 | O5: 0 | P5: 0 | Q5: 0 | R5: 0 | S5: 10875967 | T5: 2136859.8 | U5: 1995434.4 | V5: 7094690.8 | W5: 3784275.5 | X5: =SUM(D5:W5) -> 1.3143984e+09
A6: PA | B6: Pará | C6: 15 | D6: 0 | E6: 5.6448923e+08 | F6: 20090039 | G6: 27830919 | H6: 0 | I6: 8.8363938e+08 | J6: 36040938 | K6: 5085583.3 | L6: 3.8405571e+09 | M6: 0 | N6: 7.7623821e+08 | O6: 0 | P6: 0 | Q6: 1357682.2 | R6: 0 | S6: 4311455.5 | T6: 1566103.9 | U6: 8867776.6 | V6: 61891806 | W6: 25875730 | X6: =SUM(D6:W6) -> 6.257842e+09
A7: AP | B7: Amapá | C7: 16 | D7: 0 | E7: 3.2715936e+08 | F7: 258208.29 | G7: 1442685.4 | H7: 0 | I7: 52613630 | J7: 3609766.2 | K7: 134974.25 | L7: 1.0912987e+09 | M7: 0 | N7: 1.331169e+08 | O7: 0 | P7: 0 | Q7: 5231.3612 | R7: 0 | S7: 7587435.3 | T7: 2749757.2 | U7: 646410.89 | V7: 8573505.4 | W7: 6752267.2 | X7: =SUM(D7:W7) -> 1.6359488e+09
A8: TO | B8: Tocantins | C8: 17 | D8: 0 | E8: 3.7097288e+08 | F8: 498398.12 | G8: 6152733 | H8: 0 | I8: 2.1407313e+08 | J8: 14547962 | K8: 5292585.2 | L8: 1.4301919e+09 | M8: 0 | N8: 2.9306841e+08 | O8: 0 | P8: 0 | Q8: 0.4249125 | R8: 0 | S8: 21461939 | T8: 0 | U8: 4491449.8 | V8: 20340088 | W8: 7267778.4 | X8: =SUM(D8:W8) -> 2.3883592e+09
A9: MA | B9: Maranhão | C9: 21 | D9: 0 | E9: 6.4824657e+08 | F9: 3092378.1 | G9: 0 | H9: 0 | I9: 4.646972e+08 | J9: 25695418 | K9: 3551836.1 | L9: 2.2411224e+09 | M9: 0 | N9: 3.3371142e+08 | O9: 0 | P9: 0 | Q9: 2763.3278 | R9: 0 | S9: 45475152 | T9: 0 | U9: 7178063.9 | V9: 24920712 | W9: 20777338 | X9: =SUM(D9:W9) -> 3.8184713e+09
A10: PI | B10: Piauí | C10: 22 | D10: 0 | E10: 3.9556781e+08 | F10: 69228.318 | G10: 12590157 | H10: 0 | I10: 2.8748532e+08 | J10: 15558911 | K10: 2027257.3 | L10: 1.806258e+09 | M10: 0 | N10: 2.0616498e+08 | O10: 0 | P10: 0 | Q10: 41.117366 | R10: 0 | S10: 33572387 | T10: 6685914 | U10: 4778124.1 | V10: 19631055 | W10: 10368095 | X10: =SUM(D10:W10) -> 2.8007572e+09
A11: CE | B11: Ceará | C11: 23 | D11: 0 | E11: 6.4636529e+08 | F11: 2356314.8 | G11: 20596784 | H11: 0 | I11: 7.3327037e+08 | J11: 53281874 | K11: 6289153.7 | L11: 3.0584546e+09 | M11: 0 | N11: 6.2164811e+08 | O11: 0 | P11: 0 | Q11: 16.415786 | R11: 0 | S11: 80533868 | T11: 3123081.7 | U11: 10207622 | V11: 98017209 | W11: 23317422 | X11: =SUM(D11:W11) -> 5.3574617e+09
A12: RN | B12: Rio Grande do Norte | C12: 24 | D12: 0 | E12: 3.5708145e+08 | F12: 728491.74 | G12: 10906222 | H12: 0 | I12: 3.5221881e+08 | J12: 18272162 | K12: 1698810.8 | L12: 1.5993232e+09 | M12: 0 | N12: 4.4355796e+08 | O12: 0 | P12: 0 | Q12: 21417.414 | R12: 0 | S12: 29778805 | T12: 467611.84 | U12: 6077523.5 | V12: 32742990 | W12: 13007566 | X12: =SUM(D12:W12) -> 2.865883e+09
A13: PB | B13: Paraíba | C13: 25 | D13: 0 | E13: 4.3005528e+08 | F13: 160499.65 | G13: 17136721 | H13: 0 | I13: 3.4370034e+08 | J13: 19615020 | K13: 9276048.5 | L13: 1.830409e+09 | M13: 0 | N13: 2.6347018e+08 | O13: 0 | P13: 0 | Q13: 61129.669 | R13: 0 | S13: 29813922 | T13: 0 | U13: 6121346.1 | V13: 32446369 | W13: 13190186 | X13: =SUM(D13:W13) -> 2.9954561e+09
... A5596: GO | B5596: Vila Propício | C5596: 5222302 | D5596: 1095091.5 | E5596: 0 | F5596: 5919.105 | G5596: 0 | H5596: 65434.892 | I5596: 987512.4 | J5596: 23084.267 | K5596: 0 | L5596: 5287218.9 | M5596: 0 | N5596: 178580.7 | O5596: 476832.27 | P5596: 739549.76 | Q5596: 0 | R5596: 0 | S5596: 102634.39 | T5596: 0 | U5596: 0 | V5596: 234153.64 | W5596: 47461.808 | X5596: =SUM(D5596:W5596) -> 9243473.6
A5597: Total Brasil | D5597: 1.4331203e+10 | E5597: 9.1539118e+09 | F5597: 3.3164855e+08 | G5597: 9.1331193e+08 | H5597: 1.6151841e+08 | I5597: 3.9746447e+10 | J5597: 4.6013762e+09 | K5597: 8.798749e+08 | L5597: 2.879487e+11 | M5597: 2.0548457e+10 | N5597: 3.2241341e+10 | O5597: 6.0623378e+09 | P5597: 3.4663914e+10 | Q5597: 12420886 | R5597: 9.0233328e+09 | S5597: =SUM(S2:S5596) -> 5.9830639e+09 | T5597: =SUM(T2:T5596) -> 9.8810621e+08 | U5597: =SUM(U2:U5596) -> 1.0985566e+09 | V5597: =SUM(V2:V5596) -> 2.0579309e+10 | W5597: =SUM(W2:W5596) -> 2.0095439e+09 | X5597: =SUM(X2:X5596) -> 4.9127837e+11

Sheet NOMINAL
A1: UF | B1: Ente Federado | C1: Código IBGE | D1: FPM | E1: FPE | F1: IPI-Exp | G1: AFE EC 123 | H1: ITR | I1: ICMS | J1: IPVA | K1: ITCMD | L1: Fundeb (Contribuição e complementação VAAF) | M1: IPTU | N1: IRRF | O1: ITBI | P1: ISS | Q1: IOF-Ouro | R1: Petróleo e Gás | S1: TOTAL GERAL | U1: UF | V1: Ente Federado | W1: Código IBGE | X1: PNAE | Y1: PNATE | Z1: PDDE | AA1: Quotas Estaduais e Municipais do Salário-Educação | AB1: PNLD | AC1: Total
A2: RO | B2: Rondônia | C2: 11 | D2: ='COM CORREÇÃO'!D2/1.1331 -> 0 | E2: ='COM CORREÇÃO'!E2/1.1331 -> 2.3961981e+08 | F2: ='COM CORREÇÃO'!F2/1.1331 -> 913365.98 | G2: ='COM CORREÇÃO'!G2/1.1331 -> 10230000 | H2: ='COM CORREÇÃO'!H2/1.1331 -> 0 | I2: ='COM CORREÇÃO'!I2/1.1331 -> 2.2967904e+08 | J2: ='COM CORREÇÃO'!J2/1.1331 -> 15732248 | K2: ='COM CORREÇÃO'!K2/1.1331 -> 1607619.1 | ... R2: ='COM CORREÇÃO'!R2/1.1331 -> 0 | S2: ='COM CORREÇÃO'!#REF!/1.1331 -> #REF! | U2: AC | V2: ACRE | W2: 12 | X2: 12663244 | Y2: 3925191.6 | Z2: 4253250 | AA2: 10378119 | AB2: 5941893.1 | AC2: =SUM(X2:AB2) -> 37161698
A3: AC | B3: Acre | C3: 12 | D3: ='COM CORREÇÃO'!D3/1.1331 -> 0 | E3: ='COM CORREÇÃO'!E3/1.1331 -> 2.8667664e+08 | F3: ='COM CORREÇÃO'!F3/1.1331 -> 33551.208 | G3: ='COM CORREÇÃO'!G3/1.1331 -> 2250001.1 | H3: ='COM CORREÇÃO'!H3/1.1331 -> 0 | I3: ='COM CORREÇÃO'!I3/1.1331 -> 71704971 | J3: ='COM CORREÇÃO'!J3/1.1331 -> 3288306.8 | K3: ='COM CORREÇÃO'!K3/1.1331 -> 784893 | ... R3: ='COM CORREÇÃO'!R3/1.1331 -> 0 | S3: ='COM CORREÇÃO'!#REF!/1.1331 -> #REF! | U3: AC | V3: ACRELANDIA | W3: 1200013 | X3: 275380.94 | Y3: 63171.14 | Z3: 54250 | AA3: 151361.2 | AB3: 118981.52 | AC3: =SUM(X3:AB3) -> 663144.8
A4: AM | B4: Amazonas | C4: 13 | D4: ='COM CORREÇÃO'!D4/1.1331 -> 0 | E4: ='COM CORREÇÃO'!E4/1.1331 -> 2.7176803e+08 | F4: ='COM CORREÇÃO'!F4/1.1331 -> 998288.91 | G4: ='COM CORREÇÃO'!G4/1.1331 -> 5160000 | H4: ='COM CORREÇÃO'!H4/1.1331 -> 0 | I4: ='COM CORREÇÃO'!I4/1.1331 -> 5.3474356e+08 | J4: ='COM CORREÇÃO'!J4/1.1331 -> 19514839 | K4: ='COM CORREÇÃO'!K4/1.1331 -> 2310244.8 | ... R4: ='COM CORREÇÃO'!R4/1.1331 -> 0 | S4: ='COM CORREÇÃO'!#REF!/1.1331 -> #REF! | U4: AC | V4: ASSIS BRASIL | W4: 1200054 | X4: 157300.24 | Y4: 34087.03 | Z4: 58200 | AA4: 99550.02 | AB4: 99803.95 | AC4: =SUM(X4:AB4) -> 448941.24
A5: RR | B5: Roraima | C5: 14 | D5: ='COM CORREÇÃO'!D5/1.1331 -> 0 | E5: ='COM CORREÇÃO'!E5/1.1331 -> 2.256707e+08 | F5: ='COM CORREÇÃO'!F5/1.1331 -> 295441.16 | G5: ='COM CORREÇÃO'!G5/1.1331 -> 0 | H5: ='COM CORREÇÃO'!H5/1.1331 -> 0 | I5: ='COM CORREÇÃO'!I5/1.1331 -> 57543509 | J5: ='COM CORREÇÃO'!J5/1.1331 -> 2873629 | K5: ='COM CORREÇÃO'!K5/1.1331 -> 401395.44 | ... R5: ='COM CORREÇÃO'!R5/1.1331 -> 0 | S5: ='COM CORREÇÃO'!#REF!/1.1331 -> #REF! | U5: AC | V5: BRASILEIA | W5: 1200104 | X5: 408773.8 | Y5: 133748.63 | Z5: 183590 | AA5: 233792.8 | AB5: 190856.65 | AC5: =SUM(X5:AB5) -> 1150761.9
A6: PA | B6: Pará | C6: 15 | D6: ='COM CORREÇÃO'!D6/1.1331 -> 0 | E6: ='COM CORREÇÃO'!E6/1.1331 -> 4.981813e+08 | F6: ='COM CORREÇÃO'!F6/1.1331 -> 17730156 | G6: ='COM CORREÇÃO'!G6/1.1331 -> 24561750 | H6: ='COM CORREÇÃO'!H6/1.1331 -> 0 | I6: ='COM CORREÇÃO'!I6/1.1331 -> 7.7984236e+08 | J6: ='COM CORREÇÃO'!J6/1.1331 -> 31807376 | K6: ='COM CORREÇÃO'!K6/1.1331 -> 4488203.4 | ... R6: ='COM CORREÇÃO'!R6/1.1331 -> 0 | S6: ='COM CORREÇÃO'!#REF!/1.1331 -> #REF! | U6: AC | V6: BUJARI | W6: 1200138 | X6: 203730 | Y6: 0 | Z6: 0 | AA6: 113174.97 | AB6: 171858.65 | AC6: =SUM(X6:AB6) -> 488763.62
A7: AP | B7: Amapá | C7: 16 | D7: ='COM CORREÇÃO'!D7/1.1331 -> 0 | E7: ='COM CORREÇÃO'!E7/1.1331 -> 2.8872947e+08 | F7: ='COM CORREÇÃO'!F7/1.1331 -> 227877.76 | G7: ='COM CORREÇÃO'!G7/1.1331 -> 1273219.8 | H7: ='COM CORREÇÃO'!H7/1.1331 -> 0 | I7: ='COM CORREÇÃO'!I7/1.1331 -> 46433351 | J7: ='COM CORREÇÃO'!J7/1.1331 -> 3185743.7 | K7: ='COM CORREÇÃO'!K7/1.1331 -> 119119.45 | ... R7: ='COM CORREÇÃO'!R7/1.1331 -> 0 | S7: ='COM CORREÇÃO'!#REF!/1.1331 -> #REF! | U7: AC | V7: CAPIXABA | W7: 1200179 | X7: 190165.8 | Y7: 202788.37 | Z7: 56170 | AA7: 165084.69 | AB7: 113516.46 | AC7: =SUM(X7:AB7) -> 727725.32
A8: TO | B8: Tocantins | C8: 17 | D8: ='COM CORREÇÃO'!D8/1.1331 -> 0 | E8: ='COM CORREÇÃO'!E8/1.1331 -> 3.2739642e+08 | F8: ='COM CORREÇÃO'!F8/1.1331 -> 439853.6 | G8: ='COM CORREÇÃO'!G8/1.1331 -> 5430000 | H8: ='COM CORREÇÃO'!H8/1.1331 -> 0 | I8: ='COM CORREÇÃO'!I8/1.1331 -> 1.8892695e+08 | J8: ='COM CORREÇÃO'!J8/1.1331 -> 12839080 | K8: ='COM CORREÇÃO'!K8/1.1331 -> 4670889.8 | ... R8: ='COM CORREÇÃO'!R8/1.1331 -> 0 | S8: ='COM CORREÇÃO'!#REF!/1.1331 -> #REF! | U8: AC | V8: CRUZEIRO DO SUL | W8: 1200203 | X8: 1432958.2 | Y8: 457108.2 | Z8: 522980 | AA8: 822776.01 | AB8: 671212.86 | AC8: =SUM(X8:AB8) -> 3907035.2
A9: MA | B9: Maranhão | C9: 21 | D9: ='COM CORREÇÃO'!D9/1.1331 -> 0 | E9: ='COM CORREÇÃO'!E9/1.1331 -> 5.7210005e+08 | F9: ='COM CORREÇÃO'!F9/1.1331 -> 2729130.8 | G9: ='COM CORREÇÃO'!G9/1.1331 -> 0 | H9: ='COM CORREÇÃO'!H9/1.1331 -> 0 | I9: ='COM CORREÇÃO'!I9/1.1331 -> 4.1011138e+08 | J9: ='COM CORREÇÃO'!J9/1.1331 -> 22677096 | K9: ='COM CORREÇÃO'!K9/1.1331 -> 3134618.4 | ... R9: ='COM CORREÇÃO'!R9/1.1331 -> 0 | S9: ='COM CORREÇÃO'!#REF!/1.1331 -> #REF! | U9: AC | V9: EPITACIOLANDIA | W9: 1200252 | X9: 313347 | Y9: 100836.23 | Z9: 75200 | AA9: 179196.32 | AB9: 155431.74 | AC9: =SUM(X9:AB9) -> 824011.29
A10: PI | B10: Piauí | C10: 22 | D10: ='COM CORREÇÃO'!D10/1.1331 -> 0 | E10: ='COM CORREÇÃO'!E10/1.1331 -> 3.4910229e+08 | F10: ='COM CORREÇÃO'!F10/1.1331 -> 61096.389 | G10: ='COM CORREÇÃO'!G10/1.1331 -> 11111250 | H10: ='COM CORREÇÃO'!H10/1.1331 -> 0 | I10: ='COM CORREÇÃO'!I10/1.1331 -> 2.5371575e+08 | J10: ='COM CORREÇÃO'!J10/1.1331 -> 13731278 | K10: ='COM CORREÇÃO'!K10/1.1331 -> 1789124.8 | ... R10: ='COM CORREÇÃO'!R10/1.1331 -> 0 | S10: ='COM CORREÇÃO'!#REF!/1.1331 -> #REF! | U10: AC | V10: FEIJO | W10: 1200302 | X10: 505498.6 | Y10: 332704.14 | Z10: 392920 | AA10: 322892.63 | AB10: 366123.07 | AC10: =SUM(X10:AB10) -> 1920138.4
A11: CE | B11: Ceará | C11: 23 | D11: ='COM CORREÇÃO'!D11/1.1331 -> 0 | E11: ='COM CORREÇÃO'!E11/1.1331 -> 5.7043976e+08 | F11: ='COM CORREÇÃO'!F11/1.1331 -> 2079529.5 | G11: ='COM CORREÇÃO'!G11/1.1331 -> 18177375 | H11: ='COM CORREÇÃO'!H11/1.1331 -> 0 | I11: ='COM CORREÇÃO'!I11/1.1331 -> 6.471365e+08 | J11: ='COM CORREÇÃO'!J11/1.1331 -> 47023099 | K11: ='COM CORREÇÃO'!K11/1.1331 -> 5550396 | ... R11: ='COM CORREÇÃO'!R11/1.1331 -> 0 | S11: ='COM CORREÇÃO'!#REF!/1.1331 -> #REF! | U11: AC | V11: JORDAO | W11: 1200328 | X11: 380474.6 | Y11: 336066.44 | Z11: 200790 | AA11: 190151.73 | AB11: 205917.5 | AC11: =SUM(X11:AB11) -> 1313400.3
A12: RN | B12: Rio Grande do Norte | C12: 24 | D12: ='COM CORREÇÃO'!D12/1.1331 -> 0 | E12: ='COM CORREÇÃO'!E12/1.1331 -> 3.1513675e+08 | F12: ='COM CORREÇÃO'!F12/1.1331 -> 642919.19 | G12: ='COM CORREÇÃO'!G12/1.1331 -> 9625118.8 | H12: ='COM CORREÇÃO'!H12/1.1331 -> 0 | I12: ='COM CORREÇÃO'!I12/1.1331 -> 3.108453e+08 | J12: ='COM CORREÇÃO'!J12/1.1331 -> 16125816 | K12: ='COM CORREÇÃO'!K12/1.1331 -> 1499259.3 | ... R12: ='COM CORREÇÃO'!R12/1.1331 -> 0 | S12: ='COM CORREÇÃO'!#REF!/1.1331 -> #REF! | U12: AC | V12: MANCIO LIMA | W12: 1200336 | X12: 499235 | Y12: 185797.73 | Z12: 151890 | AA12: 227861.41 | AB12: 181155.31 | AC12: =SUM(X12:AB12) -> 1245939.4
A13: PB | B13: Paraíba | C13: 25 | D13: ='COM CORREÇÃO'!D13/1.1331 -> 0 | E13: ='COM CORREÇÃO'!E13/1.1331 -> 3.7953868e+08 | F13: ='COM CORREÇÃO'!F13/1.1331 -> 141646.51 | G13: ='COM CORREÇÃO'!G13/1.1331 -> 15123750 | H13: ='COM CORREÇÃO'!H13/1.1331 -> 0 | I13: ='COM CORREÇÃO'!I13/1.1331 -> 3.0332746e+08 | J13: ='COM CORREÇÃO'!J13/1.1331 -> 17310934 | K13: ='COM CORREÇÃO'!K13/1.1331 -> 8186434.1 | ... R13: ='COM CORREÇÃO'!R13/1.1331 -> 0 | S13: ='COM CORREÇÃO'!#REF!/1.1331 -> #REF! | U13: AC | V13: MANOEL URBANO | W13: 1200344 | X13: 288231.6 | Y13: 131778.11 | Z13: 72550 | AA13: 170709.28 | AB13: 150383.74 | AC13: =SUM(X13:AB13) -> 813652.73
... A5596: GO | B5596: Vila Propício | C5596: 5222302 | D5596: ='COM CORREÇÃO'!D5596/1.1331 -> 966456.15 | E5596: ='COM CORREÇÃO'!E5596/1.1331 -> 0 | F5596: ='COM CORREÇÃO'!F5596/1.1331 -> 5223.8152 | G5596: ='COM CORREÇÃO'!G5596/1.1331 -> 0 | H5596: ='COM CORREÇÃO'!H5596/1.1331 -> 57748.559 | I5596: ='COM CORREÇÃO'!I5596/1.1331 -> 871513.9 | J5596: ='COM CORREÇÃO'!J5596/1.1331 -> 20372.666 | K5596: ='COM CORREÇÃO'!K5596/1.1331 -> 0 | ... R5596: ='COM CORREÇÃO'!R5596/1.1331 -> 0 | S5596: ='COM CORREÇÃO'!#REF!/1.1331 -> #REF! | U5596: TO | V5596: XAMBIOA | W5596: 1722107 | X5596: 228207.6 | Y5596: 52310.26 | Z5596: 47030 | AA5596: 208508.78 | AB5596: 69675.4 | AC5596: =SUM(X5596:AB5596) -> 605732.04
A5597: Total Brasil | D5597: ='COM CORREÇÃO'!D5597/1.1331 -> 1.2647783e+10 | E5597: ='COM CORREÇÃO'!E5597/1.1331 -> 8.0786443e+09 | F5597: ='COM CORREÇÃO'!F5597/1.1331 -> 2.9269133e+08 | G5597: ='COM CORREÇÃO'!G5597/1.1331 -> 8.0602942e+08 | H5597: ='COM CORREÇÃO'!H5597/1.1331 -> 1.4254559e+08 | I5597: ='COM CORREÇÃO'!I5597/1.1331 -> 3.5077617e+10 | J5597: ='COM CORREÇÃO'!J5597/1.1331 -> 4.0608738e+09 | K5597: ='COM CORREÇÃO'!K5597/1.1331 -> 7.7652007e+08 | ... R5597: ='COM CORREÇÃO'!R5597/1.1331 -> 7.9634038e+09 | S5597: ='COM CORREÇÃO'!#REF!/1.1331 -> #REF!
